htmloutput/__init__.py
htmloutput/htmloutput.py
htmloutput/nose_wrapper.py
htmloutput/version.py
nosehtmloutput-0.0.7.dist-info/METADATA
nosehtmloutput-0.0.7.dist-info/WHEEL
nosehtmloutput-0.0.7.dist-info/entry_points.txt
nosehtmloutput-0.0.7.dist-info/top_level.txt
nosehtmloutput-0.0.7.dist-info/RECORD
